util_pkg/__init__.py
gdutilpy_pkg_dubey.girish2-0.0.1.dist-info/LICENSE
gdutilpy_pkg_dubey.girish2-0.0.1.dist-info/METADATA
gdutilpy_pkg_dubey.girish2-0.0.1.dist-info/WHEEL
gdutilpy_pkg_dubey.girish2-0.0.1.dist-info/top_level.txt
gdutilpy_pkg_dubey.girish2-0.0.1.dist-info/RECORD
