Metadata-Version: 2.1
Name: gdutilpy-pkg-dubey.girish2
Version: 0.0.1
Summary: A util package
Home-page: https://github.com/girishdubey/gdutilpy
Author: Girish Dubey
Author-email: dubey.girish2@gmail.com
License: UNKNOWN
Platform: UNKNOWN
Classifier: Programming Language :: Python :: 3
Classifier: License :: OSI Approved :: MIT License
Classifier: Operating System :: OS Independent
Requires-Python: >=3.6
